se_import/__init__.py
se_import/aes.py
se_import/readme.py
se_import/se_import.so
se_import/test_import.py
se_import/version_config.py
se_import-0.0.9.dist-info/METADATA
se_import-0.0.9.dist-info/WHEEL
se_import-0.0.9.dist-info/top_level.txt
se_import-0.0.9.dist-info/RECORD
